TicTacToeAI.py
TicTacToeAI-0.0.4.dist-info/LICENSE
TicTacToeAI-0.0.4.dist-info/METADATA
TicTacToeAI-0.0.4.dist-info/WHEEL
TicTacToeAI-0.0.4.dist-info/top_level.txt
TicTacToeAI-0.0.4.dist-info/RECORD
