Metadata-Version: 2.1
Name: TicTacToeAI
Version: 0.0.4
Summary: Tic Tac Toe with AI.
Home-page: https://github.com/ujjwalredd/Tic-Tac-Toe-with-AI
Author: Ujjwal Reddy K S
License: UNKNOWN
Keywords: MinMax,Diffcult,AI
Platform: UNKNOWN
Classifier: Programming Language :: Python :: 3
Classifier: License :: OSI Approved :: MIT License
Classifier: Operating System :: OS Independent
Requires-Python: >=3.6
License-File: LICENSE
Requires-Dist: numpy
